{
  "unique_set_id": "63631",
  "results": [
    {
      "unique_set_id": "63631_6I0C1TOX",
      "question_idx": 0,
      "answer": [
        "A"
      ],
      "logprob": [
        [
          {
            "logprob": -0.00033546583,
            "bytes": [
              65
            ]
          },
          {
            "logprob": -8.000336,
            "bytes": [
              66
            ]
          }
        ]
      ],
      "is_correct_option_first": true
    },
    {
      "unique_set_id": "63631_6I0C1TOX",
      "question_idx": 0,
      "answer": [
        "B"
      ],
      "logprob": [
        [
          {
            "logprob": -4.8425554e-06,
            "bytes": [
              66
            ]
          },
          {
            "logprob": -12.250005,
            "bytes": [
              65
            ]
          }
        ]
      ],
      "is_correct_option_first": false
    },
    {
      "unique_set_id": "63631_6I0C1TOX",
      "question_idx": 1,
      "answer": [
        "A"
      ],
      "logprob": [
        [
          {
            "logprob": -0.63259906,
            "bytes": [
              65
            ]
          },
          {
            "logprob": -0.75759906,
            "bytes": [
              66
            ]
          }
        ]
      ],
      "is_correct_option_first": true
    },
    {
      "unique_set_id": "63631_6I0C1TOX",
      "question_idx": 1,
      "answer": [
        "B"
      ],
      "logprob": [
        [
          {
            "logprob": -0.0009114635,
            "bytes": [
              66
            ]
          },
          {
            "logprob": -7.000911,
            "bytes": [
              65
            ]
          }
        ]
      ],
      "is_correct_option_first": false
    }
  ]
}